async_pubsub_py/__about__.py
async_pubsub_py/__init__.py
async_pubsub_py-0.0.1.dist-info/METADATA
async_pubsub_py-0.0.1.dist-info/WHEEL
async_pubsub_py-0.0.1.dist-info/licenses/LICENSE.txt
async_pubsub_py-0.0.1.dist-info/RECORD
